veriskgo/__init__.py
veriskgo/asgi_middleware.py
veriskgo/bedrock_observe.py
veriskgo/cli.py
veriskgo/cli_doctor.py
veriskgo/cli_instrument.py
veriskgo/config.py
veriskgo/core/__init__.py
veriskgo/core/decorators.py
veriskgo/core/pricing.py
veriskgo/core/usage.py
veriskgo/integrations/__init__.py
veriskgo/integrations/aws.py
veriskgo/llm.py
veriskgo/models.py
veriskgo/sqs.py
veriskgo/trace_manager.py
veriskgo/user.py
veriskgo-38.0.0.dist-info/WHEEL
veriskgo-38.0.0.dist-info/entry_points.txt
veriskgo-38.0.0.dist-info/METADATA
veriskgo-38.0.0.dist-info/RECORD
