Metadata-Version: 2.3
Name: veriskgo
Version: 38.0.0
Summary: This package helps to abstract Gen Ai applications' observability using Langfuse.
Requires-Dist: astor
Requires-Dist: boto3
Requires-Dist: python-dotenv
Requires-Dist: wrapt
Requires-Python: >=3.9
